martor/__init__.py
martor/admin.py
martor/api.py
martor/fields.py
martor/models.py
martor/settings.py
martor/urls.py
martor/utils.py
martor/views.py
martor/widgets.py
martor/extensions/__init__.py
martor/extensions/del_ins.py
martor/extensions/emoji.py
martor/extensions/escape_html.py
martor/extensions/mdx_add_id.py
martor/extensions/mdx_video.py
martor/extensions/mention.py
martor/extensions/urlize.py
martor/locale/en/LC_MESSAGES/django.mo
martor/locale/en/LC_MESSAGES/django.po
martor/locale/id/LC_MESSAGES/django.mo
martor/locale/id/LC_MESSAGES/django.po
martor/locale/tr/LC_MESSAGES/django.mo
martor/locale/tr/LC_MESSAGES/django.po
martor/static/dicts/README.md
martor/static/dicts/en_US.aff
martor/static/dicts/en_US.dic
martor/static/martor/css/martor-admin.css
martor/static/martor/css/martor-admin.min.css
martor/static/martor/css/martor.bootstrap.css
martor/static/martor/css/martor.bootstrap.min.css
martor/static/martor/css/martor.semantic.css
martor/static/martor/css/martor.semantic.min.css
martor/static/martor/js/martor.bootstrap.js
martor/static/martor/js/martor.bootstrap.min.js
martor/static/martor/js/martor.semantic.js
martor/static/martor/js/martor.semantic.min.js
martor/static/plugins/css/ace.min.css
martor/static/plugins/css/bootstrap.min.css
martor/static/plugins/css/highlight.min.css
martor/static/plugins/css/main-1.png
martor/static/plugins/css/main-10.svg
martor/static/plugins/css/main-11.svg
martor/static/plugins/css/main-12.svg
martor/static/plugins/css/main-13.png
martor/static/plugins/css/main-14.png
martor/static/plugins/css/main-15.png
martor/static/plugins/css/main-16.png
martor/static/plugins/css/main-17.png
martor/static/plugins/css/main-18.png
martor/static/plugins/css/main-19.png
martor/static/plugins/css/main-2.png
martor/static/plugins/css/main-20.png
martor/static/plugins/css/main-21.png
martor/static/plugins/css/main-22.png
martor/static/plugins/css/main-23.png
martor/static/plugins/css/main-24.png
martor/static/plugins/css/main-25.svg
martor-1.7.15.dist-info/METADATA
martor-1.7.15.dist-info/WHEEL
martor-1.7.15.dist-info/licenses/LICENSE
martor-1.7.15.dist-info/RECORD
