Metadata-Version: 2.4
Name: martor
Version: 1.7.15
Summary: Django Markdown Editor
Project-URL: Homepage, https://github.com/agusmakmun/django-markdown-editor
Project-URL: Documentation, https://github.com/agusmakmun/django-markdown-editor?tab=readme-ov-file#installation
Project-URL: Release-notes, https://github.com/agusmakmun/django-markdown-editor/releases
Project-URL: Funding, https://www.paypal.com/paypalme/summonagus
Project-URL: Source, https://github.com/agusmakmun/django-markdown-editor
Project-URL: Issues, https://github.com/agusmakmun/django-markdown-editor/issues
Project-URL: Download, https://github.com/agusmakmun/django-markdown-editor/releases
Author-email: "Agus Makmun (Summon Agus)" <summon.agus@gmail.com>
Maintainer-email: "Agus Makmun (Summon Agus)" <summon.agus@gmail.com>
License: GPL-3.0
License-File: LICENSE
Keywords: django markdown,django markdown editor,martor
Classifier: Development Status :: 5 - Production/Stable
Classifier: Environment :: Web Environment
Classifier: Framework :: Django
Classifier: Framework :: Django :: 4.2
Classifier: Framework :: Django :: 5.0
Classifier: Framework :: Django :: 5.1
Classifier: Intended Audience :: Developers
Classifier: License :: OSI Approved :: GNU General Public License v3 (GPLv3)
Classifier: Operating System :: OS Independent
Classifier: Programming Language :: JavaScript
Classifier: Programming Language :: Python
Classifier: Programming Language :: Python :: 3.9
Classifier: Programming Language :: Python :: 3.10
Classifier: Programming Language :: Python :: 3.11
Classifier: Programming Language :: Python :: 3.12
Classifier: Programming Language :: Python :: 3.13
Classifier: Topic :: Software Development :: Libraries :: Python Modules
Requires-Python: >=3.9
Requires-Dist: bleach
Requires-Dist: django>=3.2
Requires-Dist: markdown>=3.0
Requires-Dist: requests>=2.12.4
Requires-Dist: tzdata
Requires-Dist: urllib3
Requires-Dist: zipp
Provides-Extra: dev
Requires-Dist: black; extra == 'dev'
Requires-Dist: django-stubs; extra == 'dev'
Requires-Dist: flake8; extra == 'dev'
Requires-Dist: isort; extra == 'dev'
Requires-Dist: mypy; extra == 'dev'
Requires-Dist: mypy-extensions; extra == 'dev'
Requires-Dist: pytest; extra == 'dev'
Requires-Dist: pytest-django; extra == 'dev'
